daspuml_compiler
