Metadata-Version: 1.0
Name: daspuml-compiler
Version: 1.1
Summary: The project was implemented for the Theory of Compilation and Compilators class at AGH UST.
Home-page: https://gitlab.com/agh-dasp/daspuml-language
Author: Dominik Bober, Adam Klekowski, Szymon Duda, Przemysław Ziaja
Author-email: UNKNOWN
License: MIT
Keywords: UML
Platform: UNKNOWN
